makeprov/__init__.py
makeprov/config.py
makeprov/core.py
makeprov/paths.py
makeprov/prov.py
makeprov/rdfmixin.py
makeprov/snakemake.py
makeprov-0.4.3.dist-info/METADATA
makeprov-0.4.3.dist-info/WHEEL
makeprov-0.4.3.dist-info/top_level.txt
makeprov-0.4.3.dist-info/RECORD
