Metadata-Version: 2.4
Name: makeprov
Version: 0.4.3
Summary: An provenance tracking library for simple Python workflows
Author-email: Benno Kruit <b.b.kruit@amsterdamumc.nl>
License: MIT
Project-URL: Homepage, https://github.com/bennokr/makeprov
Project-URL: Documentation, https://makeprov.readthedocs.io
Project-URL: Issue Tracker, https://github.com/bennokr/makeprov/issues
Keywords: provenance,prov,workflow,python
Classifier: Programming Language :: Python :: 3
Classifier: License :: OSI Approved :: MIT License
Classifier: Operating System :: OS Independent
Requires-Dist: parse>=1.20
Provides-Extra: snakemake
Requires-Dist: snakemake; extra == "snakemake"
Provides-Extra: dev
Requires-Dist: defopt>=6; extra == "dev"
Requires-Dist: pytest; extra == "dev"
Requires-Dist: rdflib>=6.0; extra == "dev"
Requires-Dist: pyshacl>=0.20; extra == "dev"
Provides-Extra: docs
Requires-Dist: sphinx>=7; extra == "docs"
Requires-Dist: myst-parser[linkify]; extra == "docs"
Requires-Dist: sphinx-rtd-theme; extra == "docs"
Requires-Dist: sphinx-autodoc-typehints; extra == "docs"
Requires-Dist: tomli; python_version < "3.11" and extra == "docs"
